pylanco/ERP.py
pylanco/NV.py
pylanco/PC.py
pylanco/__init__.py
pylanco-0.1.11.dist-info/licenses/LICENSE
pylanco-0.1.11.dist-info/METADATA
pylanco-0.1.11.dist-info/WHEEL
pylanco-0.1.11.dist-info/top_level.txt
pylanco-0.1.11.dist-info/RECORD
