Metadata-Version: 2.4
Name: pylanco
Version: 0.1.11
License-File: LICENSE
Requires-Dist: requests<3.0,>=2.32.3
Requires-Dist: robocorp-log<4.0,>=2.9.6
Requires-Dist: beautifulsoup4<5.0,>=4.13.4
Dynamic: license-file
Dynamic: requires-dist
